libBASE/__init__.py
libBASE/core/IgBlastParser.py
libBASE/core/__init__.py
libBASE/core/libBASE.py
libBASE/core/pathconfig.py
libBASE/core/primer.py
libBASE/primerdata/README
libBASE/primerdata/createPrimerDB.py
libBASE/primerdata/primer_created_manually.py
libBASE/primerdata/specPCR_primer_2019_04_14.xlsx
libBASE/tests/__init__.py
libBASE/tests/test_1984.py
libBASE-2.0.0.dev5.dist-info/LICENSE.txt
libBASE-2.0.0.dev5.dist-info/METADATA
libBASE-2.0.0.dev5.dist-info/WHEEL
libBASE-2.0.0.dev5.dist-info/top_level.txt
libBASE-2.0.0.dev5.dist-info/RECORD
