Metadata-Version: 2.1
Name: libBASE
Version: 2.0.0.dev5
Summary: libBASE
Author-email: Johannes <johannes-programming@mailfence.com>
License:                     GNU GENERAL PUBLIC LICENSE
Project-URL: Documentation, https://pypi.org/project/libBASE
Project-URL: Download, https://pypi.org/project/libBASE/#files
Project-URL: Source, https://github.com/johannes-programming/libBASE
Classifier: Development Status :: 3 - Alpha
Classifier: License :: OSI Approved :: MIT License
Classifier: Programming Language :: Python
Classifier: Programming Language :: Python :: 3
Classifier: Programming Language :: Python :: 3 :: Only
Requires-Python: >=3.7
License-File: LICENSE.txt
Requires-Dist: BASEoriginaldata>=2.0.0.dev3
Requires-Dist: biopython>=1.76
Requires-Dist: openpyxl>=3.0.3
